{
	"tags": null,
	"position": [
		0,
		0,
		-0.001683451235294342
	],
	"rotation": [
		0,
		0,
		0
	],
	"rotationQuaternion": [
		0,
		0,
		0,
		1
	],
	"scaling": [
		1,
		1,
		1
	],
	"billboardMode": 0,
	"scalingDeterminant": 1,
	"infiniteDistance": false,
	"ignoreNonUniformScaling": false,
	"reIntegrateRotationIntoRotationQuaternion": false,
	"name": "foot feet _end",
	"id": "ef04a626-7c0f-454f-b4c4-626c79727662",
	"state": "",
	"metadata": {},
	"type": "TransformNode",
	"uniqueId": 204,
	"parentId": "d1b69afe-a867-4e95-beae-498e85930e4d",
	"localMatrix": {
		"0": 1,
		"1": 0,
		"2": 0,
		"3": 0,
		"4": 0,
		"5": 1,
		"6": 0,
		"7": 0,
		"8": 0,
		"9": 0,
		"10": 1,
		"11": 0,
		"12": 0,
		"13": 0,
		"14": 0,
		"15": 1
	},
	"isEnabled": true
}